.coveragerc
.stestr.conf
.travis.yml
AUTHORS
CHANGELOG.md
ChangeLog
LICENSE
MANIFEST.in
README.md
openstack-common.conf
requirements.txt
setup.cfg
setup.py
test-requirements.txt
tox.ini
ironic_oneview_cli/__init__.py
ironic_oneview_cli/common.py
ironic_oneview_cli/exceptions.py
ironic_oneview_cli/facade.py
ironic_oneview_cli/service_logging.py
ironic_oneview_cli/shell.py
ironic_oneview_cli.egg-info/PKG-INFO
ironic_oneview_cli.egg-info/SOURCES.txt
ironic_oneview_cli.egg-info/dependency_links.txt
ironic_oneview_cli.egg-info/entry_points.txt
ironic_oneview_cli.egg-info/not-zip-safe
ironic_oneview_cli.egg-info/pbr.json
ironic_oneview_cli.egg-info/requires.txt
ironic_oneview_cli.egg-info/top_level.txt
ironic_oneview_cli/create_flavor_shell/__init__.py
ironic_oneview_cli/create_flavor_shell/commands.py
ironic_oneview_cli/create_flavor_shell/objects.py
ironic_oneview_cli/create_node_shell/__init__.py
ironic_oneview_cli/create_node_shell/commands.py
ironic_oneview_cli/create_port_shell/__init__.py
ironic_oneview_cli/create_port_shell/commands.py
ironic_oneview_cli/delete_node_shell/__init__.py
ironic_oneview_cli/delete_node_shell/commands.py
ironic_oneview_cli/genrc/__init__.py
ironic_oneview_cli/genrc/commands.py
ironic_oneview_cli/tests/__init__.py
ironic_oneview_cli/tests/stubs.py
ironic_oneview_cli/tests/functional/__init__.py
ironic_oneview_cli/tests/functional/test_functional_ironic_oneview_cli.py
ironic_oneview_cli/tests/integration/__init__.py
ironic_oneview_cli/tests/unit/__init__.py
ironic_oneview_cli/tests/unit/test_common.py
ironic_oneview_cli/tests/unit/test_unit_ironic_oneview_cli.py