Metadata-Version: 1.1
Name: ironic-oneview-cli
Version: 1.2.0
Summary: Command Line Interface to ease the use of OneView Driver for Ironic
Home-page: http://git.lsd.ufcg.edu.br/ironic-drivers/ironic-oneview-cli
Author: OpenStack
Author-email: thiagop@lsd.ufcg.edu.br
License: UNKNOWN
Platform: UNKNOWN
Classifier: Environment :: OpenStack
Classifier: Intended Audience :: Information Technology
Classifier: Intended Audience :: System Administrators
Classifier: License :: OSI Approved :: Apache Software License
Classifier: Operating System :: POSIX :: Linux
Classifier: Programming Language :: Python
Classifier: Programming Language :: Python :: 2
Classifier: Programming Language :: Python :: 2.7
Classifier: Programming Language :: Python :: 3
Classifier: Programming Language :: Python :: 3.3
Classifier: Programming Language :: Python :: 3.4
